tigopesasdk/__init__.py
tigopesasdk-0.1.0.dist-info/LICENSE
tigopesasdk-0.1.0.dist-info/METADATA
tigopesasdk-0.1.0.dist-info/WHEEL
tigopesasdk-0.1.0.dist-info/top_level.txt
tigopesasdk-0.1.0.dist-info/RECORD
