Metadata-Version: 2.1
Name: tigopesasdk
Version: 0.1.0
Summary: Tigo Push Pay API wrapper
Home-page: https://github.com/piusalfred/tigopesasdk
Author: Pius Alfred
Author-email: me.pius1102@gmail.com
License: UNKNOWN
Project-URL: Bug Tracker, https://github.com/piusalfred/tigopesasdk/issues
Platform: UNKNOWN
Classifier: Programming Language :: Python :: 3
Classifier: License :: OSI Approved :: MIT License
Classifier: Operating System :: OS Independent
Requires-Python: >=3.9
License-File: LICENSE
